{
    "Name": "production-rate-management",
    "DataSourceType": "Blob Storage",
    "BlobStorageProperties": {
        "StorageAccounts": [
            {
                "AccountName": "storageaccountiotul",
                "AccountKey": null
            }
        ],
        "Container": "production-rate-management",
        "PathPattern": "",
        "DateFormat": "yyyy/MM/dd",
        "TimeFormat": "HH",
        "AuthenticationMode": "ConnectionString",
        "BlobWriteMode": "Append"
    },
    "DataSourceCredentialDomain": "55393132-0600-4fc6-9958-f4699bb140be.StreamAnalystics",
    "Serialization": {
        "Type": "Json",
        "Encoding": "UTF8",
        "Format": "LineSeparated"
    },
    "MinimumRows": null,
    "MaximumTime": null,
    "ScriptType": "Output"
}